{"_id": "582ee87d57e47515848bbbd6", "displayName": {"text": "", "languageTypeId": "639-2%3AENG%40ISO", "scriptTypeId": "15924%3ALATN%40ISO", "formatTypeId": "TextFormats%3APLAIN%40okapia.net"}, "description": {"text": "", "languageTypeId": "639-2%3AENG%40ISO", "scriptTypeId": "15924%3ALATN%40ISO", "formatTypeId": "TextFormats%3APLAIN%40okapia.net"}, "recordTypeIds": ["logging.LogEntry%3Atext-blob%40ODL.MIT.EDU"], "text": {"text": "{\"params\": \"focused\", \"event_type\": \"focus\", \"session_id\": \"909e1def-348f-4dbd-c04c-1881a2c42625\", \"app_name\": \"unplatform\"}", "languageTypeId": "639-2%3AENG%40ISO", "formatTypeId": "TextFormats%3APLAIN%40okapia.net", "scriptTypeId": "15924%3ALATN%40ISO"}, "priorityId": "NoneType%3ANONE%40dlkit.mit.edu", "genusTypeId": "GenusType%3ADEFAULT%40DLKIT.MIT.EDU", "timestamp": {"hour": 11, "month": 11, "second": 41, "microsecond": 373000, "year": 2016, "tzinfo": null, "day": 18, "minute": 39}, "assignedLogIds": ["logging.Log%3A582ecb5557e475083cf0673d%40ODL.MIT.EDU"], "agentId": "osid.agent.Agent%3A909e1def-348f-4dbd-c04c-1881a2c42625%40MIT-ODL"}