{"displayName": {"text": "eb_u01l10a09", "languageTypeId": "639-2%3AENG%40ISO", "formatTypeId": "TextFormats%3APLAIN%40okapia.net", "scriptTypeId": "15924%3ALATN%40ISO"}, "description": {"text": "", "languageTypeId": "639-2%3AENG%40ISO", "scriptTypeId": "15924%3ALATN%40ISO", "formatTypeId": "TextFormats%3APLAIN%40okapia.net"}, "recordTypeIds": ["osid-object%3Asimple-child-sequencing%40ODL.MIT.EDU"], "levelId": "", "childIds": ["assessment_authoring.AssessmentPart%3A57f49dc4b3fcec3154d6b19d%40ODL.MIT.EDU"], "genusTypeId": "GenusType%3ADEFAULT%40DLKIT.MIT.EDU", "assignedBankIds": ["assessment.Bank%3A57f49d8db3fcec3154d6b0e3%40ODL.MIT.EDU"], "_id": "57f49dc4b3fcec3154d6b19c", "rubricId": ""}