{"displayName": {"text": "ee_u1l08a04", "languageTypeId": "639-2%3AENG%40ISO", "formatTypeId": "TextFormats%3APLAIN%40okapia.net", "scriptTypeId": "15924%3ALATN%40ISO"}, "description": {"text": "", "languageTypeId": "639-2%3AENG%40ISO", "scriptTypeId": "15924%3ALATN%40ISO", "formatTypeId": "TextFormats%3APLAIN%40okapia.net"}, "recordTypeIds": ["osid-object%3Asimple-child-sequencing%40ODL.MIT.EDU"], "levelId": "", "childIds": ["assessment_authoring.AssessmentPart%3A58256cceb3fcec0e0743ad92%40ODL.MIT.EDU"], "genusTypeId": "GenusType%3ADEFAULT%40DLKIT.MIT.EDU", "assignedBankIds": ["assessment.Bank%3A58206ea2b3fcec7d0b8b6fdf%40ODL.MIT.EDU"], "_id": "58256cceb3fcec0e0743ad91", "rubricId": ""}