{"minStringLength": null, "displayName": {"text": "ee_u1l05a04q09_en", "languageTypeId": "639-2%3AENG%40ISO", "scriptTypeId": "15924%3ALATN%40ISO", "formatTypeId": "TextFormats%3APLAIN%40okapia.net"}, "description": {"text": "QTI AssessmentItem", "languageTypeId": "639-2%3AENG%40ISO", "scriptTypeId": "15924%3ALATN%40ISO", "formatTypeId": "TextFormats%3APLAIN%40okapia.net"}, "recordTypeIds": ["item-record-type%3Aqti%40ODL.MIT.EDU", "item-record-type%3Aprovenance%40ODL.MIT.EDU", "item-record-type%3Awrong-answer%40ODL.MIT.EDU"], "creationTime": {"hour": 10, "month": 9, "second": 21, "microsecond": 498918, "year": 2016, "tzinfo": null, "day": 26, "minute": 59}, "question": {"itemId": "assessment.Item%3A57e8ff89b3fcec1309c4e57e%40ODL.MIT.EDU", "shuffle": false, "description": {"text": "QTI AssessmentItem", "languageTypeId": "639-2%3AENG%40ISO", "formatTypeId": "TextFormats%3APLAIN%40okapia.net", "scriptTypeId": "15924%3ALATN%40ISO"}, "recordTypeIds": ["question-record-type%3Aqti%40ODL.MIT.EDU", "question-record-type%3Afiles%40ODL.MIT.EDU", "question-record-type%3Amulti-choice-text%40ODL.MIT.EDU"], "text": {"text": "<itemBody><p><span data-sheets-userformat='{\"2\":899,\"3\":{\"1\":0},\"4\":{\"1\":2,\"2\":9684093},\"10\":1,\"11\":4,\"12\":0}' data-sheets-value='{\"1\":2,\"2\":\"Why did Kanasu, Sahir and Zo not finish their adventure?\"}'>Why did Kanasu, Sahir and Zo not finish their adventure?</span></p><p> </p><p><span data-sheets-userformat='{\"2\":899,\"3\":{\"1\":0},\"4\":{\"1\":2,\"2\":9684093},\"10\":1,\"11\":4,\"12\":0}' data-sheets-value='{\"1\":2,\"2\":\"Why did Kanasu, Sahir and Zo not finish their adventure?\"}'><audio autoplay=\"autoplay\" controls=\"controls\" style=\"width: 125px\"><source src=\"AssetContent:ee_U01L05A04Q09_en_aud0055_mp3\" type=\"audio/mpeg\"/></audio></span></p></itemBody>", "languageTypeId": "639-2%3AENG%40ISO", "formatTypeId": "TextFormats%3APLAIN%40okapia.net", "scriptTypeId": "15924%3ALATN%40ISO"}, "choices": [{"text": "<simpleChoice identifier=\"id6c86115d-ffb4-4c01-9b8c-ad5e607bc4c8\"><p><span data-sheets-userformat=\"{\" data-sheets-value=\"{\">The stream was very big.</span></p><p><span data-sheets-userformat=\"{\" data-sheets-value=\"{\"><audio controls=\"controls\" style=\"width: 125px\"><source src=\"AssetContent:ee_U01L05A04Q09A_en_aud0056_mp3\" type=\"audio/mpeg\"/></audio></span></p></simpleChoice>", "id": "id6c86115d-ffb4-4c01-9b8c-ad5e607bc4c8", "name": ""}, {"text": "<simpleChoice identifier=\"id9024a1cf-20c7-4361-b72f-45cd5842275e\"><p><span data-sheets-userformat=\"{\" data-sheets-value=\"{\">There was no bridge to cross the stream.</span></p><p><span data-sheets-userformat=\"{\" data-sheets-value=\"{\"><audio controls=\"controls\" style=\"width: 125px\"><source src=\"AssetContent:ee_U01L05A04Q09B_en_aud0057_mp3\" type=\"audio/mpeg\"/></audio></span></p></simpleChoice>", "id": "id9024a1cf-20c7-4361-b72f-45cd5842275e", "name": ""}, {"text": "<simpleChoice identifier=\"id5380ea63-2ece-4383-ab1b-04cded6997d7\"><p><span data-sheets-userformat=\"{\" data-sheets-value=\"{\">The stones in the stream were slippery.</span></p><p><span data-sheets-userformat=\"{\" data-sheets-value=\"{\"><audio controls=\"controls\" style=\"width: 125px\"><source src=\"AssetContent:ee_U01L05A04Q09_en_aud0058_mp3\" type=\"audio/mpeg\"/></audio></span></p></simpleChoice>", "id": "id5380ea63-2ece-4383-ab1b-04cded6997d7", "name": ""}, {"text": "<simpleChoice identifier=\"id51514c41-dca9-442f-a697-361d3de2af2d\"><p><span data-sheets-userformat='{\"2\":897,\"3\":{\"1\":0},\"10\":1,\"11\":4,\"12\":0}' data-sheets-value='{\"1\":2,\"2\":\"It was getting dark.\"}'>It was getting dark.</span></p><p><span data-sheets-userformat='{\"2\":897,\"3\":{\"1\":0},\"10\":1,\"11\":4,\"12\":0}' data-sheets-value='{\"1\":2,\"2\":\"It was getting dark.\"}'><audio controls=\"controls\" style=\"width: 125px\"><source src=\"AssetContent:ee_U01L05A04Q09D_en_aud0059_mp3\" type=\"audio/mpeg\"/></audio></span></p></simpleChoice>", "id": "id51514c41-dca9-442f-a697-361d3de2af2d", "name": ""}], "genusTypeId": "question-type%3Aqti-choice-interaction%40ODL.MIT.EDU", "assignedBankIds": ["assessment.Bank%3A57e8ff6eb3fcec1309c4e3fa%40ODL.MIT.EDU"], "displayName": {"text": "ee_u1l05a04q09_en", "languageTypeId": "639-2%3AENG%40ISO", "formatTypeId": "TextFormats%3APLAIN%40okapia.net", "scriptTypeId": "15924%3ALATN%40ISO"}, "_id": "57e8ff89b3fcec1309c4e57e", "multiAnswer": false, "fileIds": {"ee_U01L05A04Q09A_en_aud0056_mp3": {"assetId": "repository.Asset%3A57e8ff89b3fcec1309c4e583%40ODL.MIT.EDU", "assetContentTypeId": "asset-content-genus-type%3Amp3%40iana.org", "assetContentId": "repository.AssetContent%3A57e8ff89b3fcec1309c4e585%40ODL.MIT.EDU"}, "ee_U01L05A04Q09D_en_aud0059_mp3": {"assetId": "repository.Asset%3A57e8ff89b3fcec1309c4e58c%40ODL.MIT.EDU", "assetContentTypeId": "asset-content-genus-type%3Amp3%40iana.org", "assetContentId": "repository.AssetContent%3A57e8ff89b3fcec1309c4e58e%40ODL.MIT.EDU"}, "ee_U01L05A04Q09_en_aud0055_mp3": {"assetId": "repository.Asset%3A57e8ff89b3fcec1309c4e580%40ODL.MIT.EDU", "assetContentTypeId": "asset-content-genus-type%3Amp3%40iana.org", "assetContentId": "repository.AssetContent%3A57e8ff89b3fcec1309c4e582%40ODL.MIT.EDU"}, "ee_U01L05A04Q09B_en_aud0057_mp3": {"assetId": "repository.Asset%3A57e8ff89b3fcec1309c4e586%40ODL.MIT.EDU", "assetContentTypeId": "asset-content-genus-type%3Amp3%40iana.org", "assetContentId": "repository.AssetContent%3A57e8ff89b3fcec1309c4e588%40ODL.MIT.EDU"}, "ee_U01L05A04Q09_en_aud0058_mp3": {"assetId": "repository.Asset%3A57e8ff89b3fcec1309c4e589%40ODL.MIT.EDU", "assetContentTypeId": "asset-content-genus-type%3Amp3%40iana.org", "assetContentId": "repository.AssetContent%3A57e8ff89b3fcec1309c4e58b%40ODL.MIT.EDU"}}}, "answers": [{"itemId": "assessment.Item%3A57e8ff89b3fcec1309c4e57e%40ODL.MIT.EDU", "displayName": {"text": "ee_u1l05a04q09_en", "languageTypeId": "639-2%3AENG%40ISO", "formatTypeId": "TextFormats%3APLAIN%40okapia.net", "scriptTypeId": "15924%3ALATN%40ISO"}, "description": {"text": "ee_u1l05a04q09_en", "languageTypeId": "639-2%3AENG%40ISO", "formatTypeId": "TextFormats%3APLAIN%40okapia.net", "scriptTypeId": "15924%3ALATN%40ISO"}, "recordTypeIds": ["answer-record-type%3Aqti%40ODL.MIT.EDU", "answer-record-type%3Amulti-choice-with-files-and-feedback%40ODL.MIT.EDU"], "choiceIds": ["id51514c41-dca9-442f-a697-361d3de2af2d"], "confusedLearningObjectiveIds": [], "genusTypeId": "answer-type%3Aright-answer%40ODL.MIT.EDU", "assignedBankIds": ["assessment.Bank%3A57e8ff6eb3fcec1309c4e3fa%40ODL.MIT.EDU"], "_id": "57e8ff89b3fcec1309c4e593", "feedback": {"text": "<modalFeedback identifier=\"Feedback690157500\" outcomeIdentifier=\"FEEDBACKMODAL\" showHide=\"show\" title=\"ee_u1l05a04q09DF_en\"><p><span data-sheets-userformat='{\"2\":897,\"3\":{\"1\":0},\"10\":1,\"11\":4,\"12\":0}' data-sheets-value=\"{&quot;1&quot;:2,&quot;2&quot;:&quot;That's right ! Very good! Sahir is worried that it was getting dark and so they should come back another day. You may now proceed to the next activity.&quot;}\">That's right ! Very good! Sahir is worried that it was getting dark and so they should come back another day. You may now proceed to the next activity.</span></p><p/></modalFeedback>", "languageTypeId": "639-2%3AENG%40ISO", "formatTypeId": "TextFormats%3APLAIN%40okapia.net", "scriptTypeId": "15924%3ALATN%40ISO"}, "fileIds": {}}, {"itemId": "assessment.Item%3A57e8ff89b3fcec1309c4e57e%40ODL.MIT.EDU", "displayName": {"text": "ee_u1l05a04q09_en", "languageTypeId": "639-2%3AENG%40ISO", "formatTypeId": "TextFormats%3APLAIN%40okapia.net", "scriptTypeId": "15924%3ALATN%40ISO"}, "description": {"text": "ee_u1l05a04q09_en", "languageTypeId": "639-2%3AENG%40ISO", "formatTypeId": "TextFormats%3APLAIN%40okapia.net", "scriptTypeId": "15924%3ALATN%40ISO"}, "recordTypeIds": ["answer-record-type%3Aqti%40ODL.MIT.EDU", "answer-record-type%3Amulti-choice-with-files-and-feedback%40ODL.MIT.EDU"], "choiceIds": ["id6c86115d-ffb4-4c01-9b8c-ad5e607bc4c8"], "confusedLearningObjectiveIds": [], "genusTypeId": "answer-type%3Awrong-answer%40ODL.MIT.EDU", "assignedBankIds": ["assessment.Bank%3A57e8ff6eb3fcec1309c4e3fa%40ODL.MIT.EDU"], "_id": "57e8ff89b3fcec1309c4e598", "feedback": {"text": "<modalFeedback identifier=\"Feedback770457323\" outcomeIdentifier=\"FEEDBACKMODAL\" showHide=\"show\" title=\"ee_u1l05a04q09AF_en\"><p><span data-sheets-userformat=\"{\" data-sheets-value=\"{\">Try to recall the audio you just heard. What does Kanasu say when she sees the stream? Is that the reason for their decision to go back? Try again!</span></p><p/><p> </p><p><span data-sheets-userformat='{\"2\":7107,\"3\":{\"1\":0},\"4\":{\"1\":2,\"2\":16777215},\"9\":0,\"10\":2,\"11\":4,\"12\":0,\"14\":{\"1\":2,\"2\":0},\"15\":\"Arial\"}' data-sheets-value='{\"1\":2,\"2\":\"The stones are covered with moss and will be slippery. You might fall.\\n\\nZo is right. It is also getting dark, so it may not be a good idea to go any further today. We can come another day.\"}'>The stones are covered with moss and will be slippery. You might fall.<br/><br/>Zo is right. It is also getting dark, so it may not be a good idea to go any further today. We can come another day.</span></p><p/></modalFeedback>", "languageTypeId": "639-2%3AENG%40ISO", "formatTypeId": "TextFormats%3APLAIN%40okapia.net", "scriptTypeId": "15924%3ALATN%40ISO"}, "fileIds": {}}, {"itemId": "assessment.Item%3A57e8ff89b3fcec1309c4e57e%40ODL.MIT.EDU", "displayName": {"text": "ee_u1l05a04q09_en", "languageTypeId": "639-2%3AENG%40ISO", "formatTypeId": "TextFormats%3APLAIN%40okapia.net", "scriptTypeId": "15924%3ALATN%40ISO"}, "description": {"text": "ee_u1l05a04q09_en", "languageTypeId": "639-2%3AENG%40ISO", "formatTypeId": "TextFormats%3APLAIN%40okapia.net", "scriptTypeId": "15924%3ALATN%40ISO"}, "recordTypeIds": ["answer-record-type%3Aqti%40ODL.MIT.EDU", "answer-record-type%3Amulti-choice-with-files-and-feedback%40ODL.MIT.EDU"], "choiceIds": ["id9024a1cf-20c7-4361-b72f-45cd5842275e"], "confusedLearningObjectiveIds": [], "genusTypeId": "answer-type%3Awrong-answer%40ODL.MIT.EDU", "assignedBankIds": ["assessment.Bank%3A57e8ff6eb3fcec1309c4e3fa%40ODL.MIT.EDU"], "_id": "57e8ff89b3fcec1309c4e59d", "feedback": {"text": "<modalFeedback identifier=\"Feedback1186208726\" outcomeIdentifier=\"FEEDBACKMODAL\" showHide=\"show\" title=\"ee_u1l05a04q09BF_en\"><p><span data-sheets-userformat=\"{\" data-sheets-value=\"{\">In the story you just heard, what does Sahir say about a bridge? Is that the reason for their decision to go back? Look at the other options and try again.</span></p><p/><p> </p><p><span data-sheets-userformat='{\"2\":7107,\"3\":{\"1\":0},\"4\":{\"1\":2,\"2\":16777215},\"9\":0,\"10\":2,\"11\":4,\"12\":0,\"14\":{\"1\":2,\"2\":0},\"15\":\"Arial\"}' data-sheets-value='{\"1\":2,\"2\":\"The stones are covered with moss and will be slippery. You might fall.\\n\\nZo is right. It is also getting dark, so it may not be a good idea to go any further today. We can come another day.\"}'>The stones are covered with moss and will be slippery. You might fall.<br/><br/>Zo is right. It is also getting dark, so it may not be a good idea to go any further today. We can come another day.</span></p><p/></modalFeedback>", "languageTypeId": "639-2%3AENG%40ISO", "formatTypeId": "TextFormats%3APLAIN%40okapia.net", "scriptTypeId": "15924%3ALATN%40ISO"}, "fileIds": {}}, {"itemId": "assessment.Item%3A57e8ff89b3fcec1309c4e57e%40ODL.MIT.EDU", "displayName": {"text": "ee_u1l05a04q09_en", "languageTypeId": "639-2%3AENG%40ISO", "formatTypeId": "TextFormats%3APLAIN%40okapia.net", "scriptTypeId": "15924%3ALATN%40ISO"}, "description": {"text": "ee_u1l05a04q09_en", "languageTypeId": "639-2%3AENG%40ISO", "formatTypeId": "TextFormats%3APLAIN%40okapia.net", "scriptTypeId": "15924%3ALATN%40ISO"}, "recordTypeIds": ["answer-record-type%3Aqti%40ODL.MIT.EDU", "answer-record-type%3Amulti-choice-with-files-and-feedback%40ODL.MIT.EDU"], "choiceIds": ["id5380ea63-2ece-4383-ab1b-04cded6997d7"], "confusedLearningObjectiveIds": [], "genusTypeId": "answer-type%3Awrong-answer%40ODL.MIT.EDU", "assignedBankIds": ["assessment.Bank%3A57e8ff6eb3fcec1309c4e3fa%40ODL.MIT.EDU"], "_id": "57e8ff89b3fcec1309c4e5a2", "feedback": {"text": "<modalFeedback identifier=\"Feedback1353396074\" outcomeIdentifier=\"FEEDBACKMODAL\" showHide=\"show\" title=\"ee_u1l05a04q09CF_en\"><p><span data-sheets-userformat='{\"2\":897,\"3\":{\"1\":0},\"10\":1,\"11\":4,\"12\":0}' data-sheets-value='{\"1\":2,\"2\":\"Zo warns Kanasu about stepping on slippery stones. Was that the reason for their decision to go back? Look at the other options and try again.\"}'>Zo warns Kanasu about stepping on slippery stones. Was that the reason for their decision to go back? Look at the other options and try again.</span></p><p/><p> </p><p><span data-sheets-userformat='{\"2\":7107,\"3\":{\"1\":0},\"4\":{\"1\":2,\"2\":16777215},\"9\":0,\"10\":2,\"11\":4,\"12\":0,\"14\":{\"1\":2,\"2\":0},\"15\":\"Arial\"}' data-sheets-value='{\"1\":2,\"2\":\"The stones are covered with moss and will be slippery. You might fall.\\n\\nZo is right. It is also getting dark, so it may not be a good idea to go any further today. We can come another day.\"}'>The stones are covered with moss and will be slippery. You might fall.<br/><br/>Zo is right. It is also getting dark, so it may not be a good idea to go any further today. We can come another day.</span></p><p/></modalFeedback>", "languageTypeId": "639-2%3AENG%40ISO", "formatTypeId": "TextFormats%3APLAIN%40okapia.net", "scriptTypeId": "15924%3ALATN%40ISO"}, "fileIds": {}}], "texts": {}, "creatorId": "", "assignedBankIds": ["assessment.Bank%3A57f77600b3fcec3154d6ccfb%40ODL.MIT.EDU"], "provenanceId": "", "genusTypeId": "item-genus-type%3Aqti-choice-interaction%40ODL.MIT.EDU", "_id": "57e8ff89b3fcec1309c4e57e", "maxStringLength": null, "learningObjectiveIds": []}