{"minStringLength": null, "displayName": {"text": "eb_u1l05a09q01_en", "languageTypeId": "639-2%3AENG%40ISO", "scriptTypeId": "15924%3ALATN%40ISO", "formatTypeId": "TextFormats%3APLAIN%40okapia.net"}, "description": {"text": "QTI AssessmentItem", "languageTypeId": "639-2%3AENG%40ISO", "scriptTypeId": "15924%3ALATN%40ISO", "formatTypeId": "TextFormats%3APLAIN%40okapia.net"}, "recordTypeIds": ["item-record-type%3Aqti%40ODL.MIT.EDU", "item-record-type%3Aprovenance%40ODL.MIT.EDU", "item-record-type%3Awrong-answer%40ODL.MIT.EDU"], "creationTime": {"hour": 7, "month": 9, "second": 27, "microsecond": 649268, "year": 2016, "tzinfo": null, "day": 27, "minute": 29}, "question": {"itemId": "assessment.Item%3A57ea1fd7b3fcec1309c4eaeb%40ODL.MIT.EDU", "shuffle": false, "description": {"text": "QTI AssessmentItem", "languageTypeId": "639-2%3AENG%40ISO", "formatTypeId": "TextFormats%3APLAIN%40okapia.net", "scriptTypeId": "15924%3ALATN%40ISO"}, "recordTypeIds": ["question-record-type%3Aqti%40ODL.MIT.EDU", "question-record-type%3Amulti-choice-text%40ODL.MIT.EDU"], "text": {"text": "<itemBody><p><span data-sheets-userformat=\"{\" data-sheets-value=\"{\">I can understand cause-and-effect statements.</span></p></itemBody>", "languageTypeId": "639-2%3AENG%40ISO", "formatTypeId": "TextFormats%3APLAIN%40okapia.net", "scriptTypeId": "15924%3ALATN%40ISO"}, "choices": [{"text": "<simpleChoice identifier=\"id69e946e9-443e-4eed-8d91-481b4a94c3d3\"><p><span data-sheets-userformat=\"{\" data-sheets-value=\"{\">Very easily </span></p></simpleChoice>", "id": "id69e946e9-443e-4eed-8d91-481b4a94c3d3", "name": ""}, {"text": "<simpleChoice identifier=\"ida6ee38f4-2be8-4518-8cc5-042f67a681a5\"><p><span data-sheets-userformat=\"{\" data-sheets-value=\"{\">Easily </span></p></simpleChoice>", "id": "ida6ee38f4-2be8-4518-8cc5-042f67a681a5", "name": ""}, {"text": "<simpleChoice identifier=\"idc7a0103d-da95-4399-b2e5-7da14c6aadb9\"><p><span data-sheets-userformat=\"{\" data-sheets-value=\"{\">With difficulty</span></p></simpleChoice>", "id": "idc7a0103d-da95-4399-b2e5-7da14c6aadb9", "name": ""}, {"text": "<simpleChoice identifier=\"idd45997cc-84c4-4d40-b6f7-fbab5227ade3\"><p><span data-sheets-userformat=\"{\" data-sheets-value=\"{\">With great difficulty. </span></p></simpleChoice>", "id": "idd45997cc-84c4-4d40-b6f7-fbab5227ade3", "name": ""}], "genusTypeId": "question-type%3Aqti-choice-interaction-survey%40ODL.MIT.EDU", "assignedBankIds": ["assessment.Bank%3A57ea1fd6b3fcec1309c4eae7%40ODL.MIT.EDU"], "displayName": {"text": "eb_u1l05a09q01_en", "languageTypeId": "639-2%3AENG%40ISO", "formatTypeId": "TextFormats%3APLAIN%40okapia.net", "scriptTypeId": "15924%3ALATN%40ISO"}, "_id": "57ea1fd7b3fcec1309c4eaeb", "multiAnswer": false}, "answers": [{"itemId": "assessment.Item%3A57ea1fd7b3fcec1309c4eaeb%40ODL.MIT.EDU", "displayName": {"text": "eb_u1l05a09q01_en", "languageTypeId": "639-2%3AENG%40ISO", "formatTypeId": "TextFormats%3APLAIN%40okapia.net", "scriptTypeId": "15924%3ALATN%40ISO"}, "description": {"text": "eb_u1l05a09q01_en", "languageTypeId": "639-2%3AENG%40ISO", "formatTypeId": "TextFormats%3APLAIN%40okapia.net", "scriptTypeId": "15924%3ALATN%40ISO"}, "recordTypeIds": ["answer-record-type%3Aqti%40ODL.MIT.EDU", "answer-record-type%3Amulti-choice-with-files-and-feedback%40ODL.MIT.EDU"], "choiceIds": ["id69e946e9-443e-4eed-8d91-481b4a94c3d3"], "confusedLearningObjectiveIds": [], "genusTypeId": "answer-type%3Aright-answer%40ODL.MIT.EDU", "assignedBankIds": ["assessment.Bank%3A57ea1fd6b3fcec1309c4eae7%40ODL.MIT.EDU"], "_id": "57ea1fd7b3fcec1309c4eaf0", "feedback": {"text": "<modalFeedback identifier=\"Feedback1\" outcomeIdentifier=\"FEEDBACKMODAL\" showHide=\"show\">\n    <p></p>\n    </modalFeedback>", "languageTypeId": "639-2%3AENG%40ISO", "formatTypeId": "TextFormats%3APLAIN%40okapia.net", "scriptTypeId": "15924%3ALATN%40ISO"}, "fileIds": {}}, {"itemId": "assessment.Item%3A57ea1fd7b3fcec1309c4eaeb%40ODL.MIT.EDU", "displayName": {"text": "eb_u1l05a09q01_en", "languageTypeId": "639-2%3AENG%40ISO", "formatTypeId": "TextFormats%3APLAIN%40okapia.net", "scriptTypeId": "15924%3ALATN%40ISO"}, "description": {"text": "eb_u1l05a09q01_en", "languageTypeId": "639-2%3AENG%40ISO", "formatTypeId": "TextFormats%3APLAIN%40okapia.net", "scriptTypeId": "15924%3ALATN%40ISO"}, "recordTypeIds": ["answer-record-type%3Aqti%40ODL.MIT.EDU", "answer-record-type%3Amulti-choice-with-files-and-feedback%40ODL.MIT.EDU"], "choiceIds": ["ida6ee38f4-2be8-4518-8cc5-042f67a681a5"], "confusedLearningObjectiveIds": [], "genusTypeId": "answer-type%3Aright-answer%40ODL.MIT.EDU", "assignedBankIds": ["assessment.Bank%3A57ea1fd6b3fcec1309c4eae7%40ODL.MIT.EDU"], "_id": "57ea1fd7b3fcec1309c4eaf5", "feedback": {"text": "<modalFeedback identifier=\"Feedback1\" outcomeIdentifier=\"FEEDBACKMODAL\" showHide=\"show\">\n    <p></p>\n    </modalFeedback>", "languageTypeId": "639-2%3AENG%40ISO", "formatTypeId": "TextFormats%3APLAIN%40okapia.net", "scriptTypeId": "15924%3ALATN%40ISO"}, "fileIds": {}}, {"itemId": "assessment.Item%3A57ea1fd7b3fcec1309c4eaeb%40ODL.MIT.EDU", "displayName": {"text": "eb_u1l05a09q01_en", "languageTypeId": "639-2%3AENG%40ISO", "formatTypeId": "TextFormats%3APLAIN%40okapia.net", "scriptTypeId": "15924%3ALATN%40ISO"}, "description": {"text": "eb_u1l05a09q01_en", "languageTypeId": "639-2%3AENG%40ISO", "formatTypeId": "TextFormats%3APLAIN%40okapia.net", "scriptTypeId": "15924%3ALATN%40ISO"}, "recordTypeIds": ["answer-record-type%3Aqti%40ODL.MIT.EDU", "answer-record-type%3Amulti-choice-with-files-and-feedback%40ODL.MIT.EDU"], "choiceIds": ["idc7a0103d-da95-4399-b2e5-7da14c6aadb9"], "confusedLearningObjectiveIds": [], "genusTypeId": "answer-type%3Aright-answer%40ODL.MIT.EDU", "assignedBankIds": ["assessment.Bank%3A57ea1fd6b3fcec1309c4eae7%40ODL.MIT.EDU"], "_id": "57ea1fd7b3fcec1309c4eafa", "feedback": {"text": "<modalFeedback identifier=\"Feedback1\" outcomeIdentifier=\"FEEDBACKMODAL\" showHide=\"show\">\n    <p></p>\n    </modalFeedback>", "languageTypeId": "639-2%3AENG%40ISO", "formatTypeId": "TextFormats%3APLAIN%40okapia.net", "scriptTypeId": "15924%3ALATN%40ISO"}, "fileIds": {}}, {"itemId": "assessment.Item%3A57ea1fd7b3fcec1309c4eaeb%40ODL.MIT.EDU", "displayName": {"text": "eb_u1l05a09q01_en", "languageTypeId": "639-2%3AENG%40ISO", "formatTypeId": "TextFormats%3APLAIN%40okapia.net", "scriptTypeId": "15924%3ALATN%40ISO"}, "description": {"text": "eb_u1l05a09q01_en", "languageTypeId": "639-2%3AENG%40ISO", "formatTypeId": "TextFormats%3APLAIN%40okapia.net", "scriptTypeId": "15924%3ALATN%40ISO"}, "recordTypeIds": ["answer-record-type%3Aqti%40ODL.MIT.EDU", "answer-record-type%3Amulti-choice-with-files-and-feedback%40ODL.MIT.EDU"], "choiceIds": ["idd45997cc-84c4-4d40-b6f7-fbab5227ade3"], "confusedLearningObjectiveIds": [], "genusTypeId": "answer-type%3Aright-answer%40ODL.MIT.EDU", "assignedBankIds": ["assessment.Bank%3A57ea1fd6b3fcec1309c4eae7%40ODL.MIT.EDU"], "_id": "57ea1fd7b3fcec1309c4eaff", "feedback": {"text": "<modalFeedback identifier=\"Feedback1\" outcomeIdentifier=\"FEEDBACKMODAL\" showHide=\"show\">\n    <p></p>\n    </modalFeedback>", "languageTypeId": "639-2%3AENG%40ISO", "formatTypeId": "TextFormats%3APLAIN%40okapia.net", "scriptTypeId": "15924%3ALATN%40ISO"}, "fileIds": {}}], "texts": {}, "creatorId": "", "assignedBankIds": ["assessment.Bank%3A57ea1fd6b3fcec1309c4eae7%40ODL.MIT.EDU"], "provenanceId": "", "genusTypeId": "item-genus-type%3Aqti-choice-interaction-survey%40ODL.MIT.EDU", "_id": "57ea1fd7b3fcec1309c4eaeb", "maxStringLength": null, "learningObjectiveIds": []}