{"minStringLength": null, "displayName": {"text": "", "languageTypeId": "639-2%3AENG%40ISO", "formatTypeId": "TextFormats%3APLAIN%40okapia.net", "scriptTypeId": "15924%3ALATN%40ISO"}, "description": {"text": "", "languageTypeId": "639-2%3AENG%40ISO", "formatTypeId": "TextFormats%3APLAIN%40okapia.net", "scriptTypeId": "15924%3ALATN%40ISO"}, "recordTypeIds": ["item-record-type%3Aqti%40ODL.MIT.EDU", "item-record-type%3Aprovenance%40ODL.MIT.EDU", "item-record-type%3Awrong-answer%40ODL.MIT.EDU", "osid-object%3Amulti-language%40ODL.MIT.EDU"], "creationTime": {"hour": 12, "month": 9, "second": 4, "microsecond": 953991, "year": 2016, "tzinfo": null, "day": 29, "minute": 17}, "question": {"itemId": "assessment.Item%3A57ed0640b3fcec0ee7647c40%40ODL.MIT.EDU", "shuffle": false, "description": {"text": "", "languageTypeId": "639-2%3AENG%40ISO", "scriptTypeId": "15924%3ALATN%40ISO", "formatTypeId": "TextFormats%3APLAIN%40okapia.net"}, "recordTypeIds": ["question-record-type%3Aqti%40ODL.MIT.EDU", "osid-object%3Amulti-language%40ODL.MIT.EDU", "question-record-type%3Amulti-language-multiple-choice%40ODL.MIT.EDU"], "choices": [{"texts": [{"text": "<simpleChoice identifier=\"idd0a70677-e8cf-4a27-bcfb-7818cdec6a48\"><p><span data-sheets-userformat=\"{\" data-sheets-value=\"{\">Very easily</span></p></simpleChoice>", "languageTypeId": "639-2%3AENG%40ISO", "formatTypeId": "TextFormats%3APLAIN%40okapia.net", "scriptTypeId": "15924%3ALATN%40ISO"}], "id": "idd0a70677-e8cf-4a27-bcfb-7818cdec6a48", "name": ""}, {"texts": [{"text": "<simpleChoice identifier=\"id7cfad954-db9b-445b-89eb-1f2fd57928f5\"><p><span data-sheets-userformat=\"{\" data-sheets-value=\"{\"><span data-sheets-userformat=\"{\" data-sheets-value=\"{\">Easily </span><br/></span></p></simpleChoice>", "languageTypeId": "639-2%3AENG%40ISO", "formatTypeId": "TextFormats%3APLAIN%40okapia.net", "scriptTypeId": "15924%3ALATN%40ISO"}], "id": "id7cfad954-db9b-445b-89eb-1f2fd57928f5", "name": ""}, {"texts": [{"text": "<simpleChoice identifier=\"id8ee3a19b-3e27-44e9-9e8b-468bb5830236\"><p><span data-sheets-userformat=\"{\" data-sheets-value=\"{\">With difficulty </span></p></simpleChoice>", "languageTypeId": "639-2%3AENG%40ISO", "formatTypeId": "TextFormats%3APLAIN%40okapia.net", "scriptTypeId": "15924%3ALATN%40ISO"}], "id": "id8ee3a19b-3e27-44e9-9e8b-468bb5830236", "name": ""}, {"texts": [{"text": "<simpleChoice identifier=\"id4ec8fc01-bc29-4950-9186-0e4b0ab23c60\"><p><span data-sheets-userformat='{\"2\":4355,\"3\":{\"1\":0},\"4\":{\"1\":2,\"2\":13228792},\"11\":4,\"15\":\"Arial\"}' data-sheets-value='{\"1\":2,\"2\":\"With great difficulty \"}'>With great difficulty </span></p></simpleChoice>", "languageTypeId": "639-2%3AENG%40ISO", "formatTypeId": "TextFormats%3APLAIN%40okapia.net", "scriptTypeId": "15924%3ALATN%40ISO"}], "id": "id4ec8fc01-bc29-4950-9186-0e4b0ab23c60", "name": ""}], "texts": [{"text": "<itemBody><p><span data-sheets-userformat='{\"2\":4867,\"3\":{\"1\":0},\"4\":{\"1\":2,\"2\":13228792},\"11\":4,\"12\":0,\"15\":\"Arial\"}' data-sheets-value='{\"1\":2,\"2\":\"I can talk about human qualities.\"}'>I can talk about human qualities.</span></p></itemBody>", "languageTypeId": "639-2%3AENG%40ISO", "formatTypeId": "TextFormats%3APLAIN%40okapia.net", "scriptTypeId": "15924%3ALATN%40ISO"}], "displayNames": [{"text": "eb_u01l08a09q04", "languageTypeId": "639-2%3AENG%40ISO", "formatTypeId": "TextFormats%3APLAIN%40okapia.net", "scriptTypeId": "15924%3ALATN%40ISO"}], "descriptions": [{"text": "eb_u01l08a09q04", "languageTypeId": "639-2%3AENG%40ISO", "formatTypeId": "TextFormats%3APLAIN%40okapia.net", "scriptTypeId": "15924%3ALATN%40ISO"}], "genusTypeId": "question-type%3Aqti-choice-interaction-survey%40ODL.MIT.EDU", "assignedBankIds": ["assessment.Bank%3A57ed0604b3fcec0ee7647bb1%40ODL.MIT.EDU"], "displayName": {"text": "", "languageTypeId": "639-2%3AENG%40ISO", "scriptTypeId": "15924%3ALATN%40ISO", "formatTypeId": "TextFormats%3APLAIN%40okapia.net"}, "_id": "57ed0640b3fcec0ee7647c40"}, "answers": [{"itemId": "assessment.Item%3A57ed0640b3fcec0ee7647c40%40ODL.MIT.EDU", "displayName": {"text": "", "languageTypeId": "639-2%3AENG%40ISO", "scriptTypeId": "15924%3ALATN%40ISO", "formatTypeId": "TextFormats%3APLAIN%40okapia.net"}, "description": {"text": "", "languageTypeId": "639-2%3AENG%40ISO", "scriptTypeId": "15924%3ALATN%40ISO", "formatTypeId": "TextFormats%3APLAIN%40okapia.net"}, "recordTypeIds": ["answer-record-type%3Aqti%40ODL.MIT.EDU", "answer-record-type%3Amulti-language-answer-with-feedback%40ODL.MIT.EDU", "answer-record-type%3Afiles%40ODL.MIT.EDU", "answer-record-type%3Amulti-choice-answer%40ODL.MIT.EDU"], "choiceIds": ["idd0a70677-e8cf-4a27-bcfb-7818cdec6a48"], "genusTypeId": "answer-type%3Aright-answer%40ODL.MIT.EDU", "assignedBankIds": ["assessment.Bank%3A57ed0604b3fcec0ee7647bb1%40ODL.MIT.EDU"], "_id": "57ed0640b3fcec0ee7647c42", "feedbacks": [{"text": "<modalFeedback identifier=\"Feedback1710073035\" outcomeIdentifier=\"FEEDBACKMODAL\" showHide=\"show\"><p>Thank you for your feedback.</p></modalFeedback>", "languageTypeId": "639-2%3AENG%40ISO", "formatTypeId": "TextFormats%3APLAIN%40okapia.net", "scriptTypeId": "15924%3ALATN%40ISO"}], "fileIds": {}}, {"itemId": "assessment.Item%3A57ed0640b3fcec0ee7647c40%40ODL.MIT.EDU", "displayName": {"text": "", "languageTypeId": "639-2%3AENG%40ISO", "scriptTypeId": "15924%3ALATN%40ISO", "formatTypeId": "TextFormats%3APLAIN%40okapia.net"}, "description": {"text": "", "languageTypeId": "639-2%3AENG%40ISO", "scriptTypeId": "15924%3ALATN%40ISO", "formatTypeId": "TextFormats%3APLAIN%40okapia.net"}, "recordTypeIds": ["answer-record-type%3Aqti%40ODL.MIT.EDU", "answer-record-type%3Amulti-language-answer-with-feedback%40ODL.MIT.EDU", "answer-record-type%3Afiles%40ODL.MIT.EDU", "answer-record-type%3Amulti-choice-answer%40ODL.MIT.EDU"], "choiceIds": ["id7cfad954-db9b-445b-89eb-1f2fd57928f5"], "genusTypeId": "answer-type%3Aright-answer%40ODL.MIT.EDU", "assignedBankIds": ["assessment.Bank%3A57ed0604b3fcec0ee7647bb1%40ODL.MIT.EDU"], "_id": "57ed0640b3fcec0ee7647c44", "feedbacks": [{"text": "<modalFeedback identifier=\"Feedback1710073035\" outcomeIdentifier=\"FEEDBACKMODAL\" showHide=\"show\"><p>Thank you for your feedback.</p></modalFeedback>", "languageTypeId": "639-2%3AENG%40ISO", "formatTypeId": "TextFormats%3APLAIN%40okapia.net", "scriptTypeId": "15924%3ALATN%40ISO"}], "fileIds": {}}, {"itemId": "assessment.Item%3A57ed0640b3fcec0ee7647c40%40ODL.MIT.EDU", "displayName": {"text": "", "languageTypeId": "639-2%3AENG%40ISO", "scriptTypeId": "15924%3ALATN%40ISO", "formatTypeId": "TextFormats%3APLAIN%40okapia.net"}, "description": {"text": "", "languageTypeId": "639-2%3AENG%40ISO", "scriptTypeId": "15924%3ALATN%40ISO", "formatTypeId": "TextFormats%3APLAIN%40okapia.net"}, "recordTypeIds": ["answer-record-type%3Aqti%40ODL.MIT.EDU", "answer-record-type%3Amulti-language-answer-with-feedback%40ODL.MIT.EDU", "answer-record-type%3Afiles%40ODL.MIT.EDU", "answer-record-type%3Amulti-choice-answer%40ODL.MIT.EDU"], "choiceIds": ["id8ee3a19b-3e27-44e9-9e8b-468bb5830236"], "genusTypeId": "answer-type%3Aright-answer%40ODL.MIT.EDU", "assignedBankIds": ["assessment.Bank%3A57ed0604b3fcec0ee7647bb1%40ODL.MIT.EDU"], "_id": "57ed0641b3fcec0ee7647c46", "feedbacks": [{"text": "<modalFeedback identifier=\"Feedback1710073035\" outcomeIdentifier=\"FEEDBACKMODAL\" showHide=\"show\"><p>Thank you for your feedback.</p></modalFeedback>", "languageTypeId": "639-2%3AENG%40ISO", "formatTypeId": "TextFormats%3APLAIN%40okapia.net", "scriptTypeId": "15924%3ALATN%40ISO"}], "fileIds": {}}, {"itemId": "assessment.Item%3A57ed0640b3fcec0ee7647c40%40ODL.MIT.EDU", "displayName": {"text": "", "languageTypeId": "639-2%3AENG%40ISO", "scriptTypeId": "15924%3ALATN%40ISO", "formatTypeId": "TextFormats%3APLAIN%40okapia.net"}, "description": {"text": "", "languageTypeId": "639-2%3AENG%40ISO", "scriptTypeId": "15924%3ALATN%40ISO", "formatTypeId": "TextFormats%3APLAIN%40okapia.net"}, "recordTypeIds": ["answer-record-type%3Aqti%40ODL.MIT.EDU", "answer-record-type%3Amulti-language-answer-with-feedback%40ODL.MIT.EDU", "answer-record-type%3Afiles%40ODL.MIT.EDU", "answer-record-type%3Amulti-choice-answer%40ODL.MIT.EDU"], "choiceIds": ["id4ec8fc01-bc29-4950-9186-0e4b0ab23c60"], "genusTypeId": "answer-type%3Aright-answer%40ODL.MIT.EDU", "assignedBankIds": ["assessment.Bank%3A57ed0604b3fcec0ee7647bb1%40ODL.MIT.EDU"], "_id": "57ed0641b3fcec0ee7647c48", "feedbacks": [{"text": "<modalFeedback identifier=\"Feedback1710073035\" outcomeIdentifier=\"FEEDBACKMODAL\" showHide=\"show\"><p>Thank you for your feedback.</p></modalFeedback>", "languageTypeId": "639-2%3AENG%40ISO", "formatTypeId": "TextFormats%3APLAIN%40okapia.net", "scriptTypeId": "15924%3ALATN%40ISO"}], "fileIds": {}}], "texts": {}, "displayNames": [{"text": "eb_u01l08a09q04", "languageTypeId": "639-2%3AENG%40ISO", "formatTypeId": "TextFormats%3APLAIN%40okapia.net", "scriptTypeId": "15924%3ALATN%40ISO"}], "descriptions": [{"text": "QTI AssessmentItem", "languageTypeId": "639-2%3AENG%40ISO", "formatTypeId": "TextFormats%3APLAIN%40okapia.net", "scriptTypeId": "15924%3ALATN%40ISO"}], "creatorId": "", "assignedBankIds": ["assessment.Bank%3A57ed0604b3fcec0ee7647bb1%40ODL.MIT.EDU"], "provenanceId": "", "genusTypeId": "item-genus-type%3Aqti-choice-interaction-survey%40ODL.MIT.EDU", "_id": "57ed0640b3fcec0ee7647c40", "maxStringLength": null, "learningObjectiveIds": []}