{"minStringLength": null, "displayName": {"text": "", "languageTypeId": "639-2%3AENG%40ISO", "scriptTypeId": "15924%3ALATN%40ISO", "formatTypeId": "TextFormats%3APLAIN%40okapia.net"}, "description": {"text": "", "languageTypeId": "639-2%3AENG%40ISO", "scriptTypeId": "15924%3ALATN%40ISO", "formatTypeId": "TextFormats%3APLAIN%40okapia.net"}, "recordTypeIds": ["item-record-type%3Aqti%40ODL.MIT.EDU", "item-record-type%3Aprovenance%40ODL.MIT.EDU", "item-record-type%3Awrong-answer%40ODL.MIT.EDU", "osid-object%3Amulti-language%40ODL.MIT.EDU", "item-record-type%3Amulti-choice-randomized%40ODL.MIT.EDU"], "question": {"itemId": "assessment.Item%3A57fd0a1bb3fcec0b1b2a4be2%40ODL.MIT.EDU", "shuffle": true, "description": {"text": "", "languageTypeId": "639-2%3AENG%40ISO", "formatTypeId": "TextFormats%3APLAIN%40okapia.net", "scriptTypeId": "15924%3ALATN%40ISO"}, "recordTypeIds": ["question-record-type%3Aqti%40ODL.MIT.EDU", "osid-object%3Amulti-language%40ODL.MIT.EDU", "question-record-type%3Amulti-choice-randomized%40ODL.MIT.EDU", "question-record-type%3Afiles%40ODL.MIT.EDU", "question-record-type%3Amulti-language-ordered-choice%40ODL.MIT.EDU"], "text": {"text": "", "languageTypeId": "639-2%3AENG%40ISO", "scriptTypeId": "15924%3ALATN%40ISO", "formatTypeId": "TextFormats%3APLAIN%40okapia.net"}, "choices": [{"texts": [{"text": "<simpleChoice identifier=\"idf2a31c44-9fd1-446e-b935-dd0da63f35d2\"><p class=\"other\">A</p></simpleChoice>", "languageTypeId": "639-2%3AENG%40ISO", "formatTypeId": "TextFormats%3APLAIN%40okapia.net", "scriptTypeId": "15924%3ALATN%40ISO"}], "id": "idf2a31c44-9fd1-446e-b935-dd0da63f35d2", "name": ""}, {"texts": [{"text": "<simpleChoice identifier=\"id78c6aac9-5e58-45c3-8bc2-4f8eb2be6a83\"><p class=\"noun\">school</p></simpleChoice>", "languageTypeId": "639-2%3AENG%40ISO", "formatTypeId": "TextFormats%3APLAIN%40okapia.net", "scriptTypeId": "15924%3ALATN%40ISO"}], "id": "id78c6aac9-5e58-45c3-8bc2-4f8eb2be6a83", "name": ""}, {"texts": [{"text": "<simpleChoice identifier=\"idf81b76d8-f298-4323-b6b9-44b22f7ce2b2\"><p class=\"noun\">bus</p></simpleChoice>", "languageTypeId": "639-2%3AENG%40ISO", "formatTypeId": "TextFormats%3APLAIN%40okapia.net", "scriptTypeId": "15924%3ALATN%40ISO"}], "id": "idf81b76d8-f298-4323-b6b9-44b22f7ce2b2", "name": ""}, {"texts": [{"text": "<simpleChoice identifier=\"id2db910f2-0e35-42da-9423-3f2a4968cc65\"><p class=\"verb\">is</p></simpleChoice>", "languageTypeId": "639-2%3AENG%40ISO", "formatTypeId": "TextFormats%3APLAIN%40okapia.net", "scriptTypeId": "15924%3ALATN%40ISO"}], "id": "id2db910f2-0e35-42da-9423-3f2a4968cc65", "name": ""}, {"texts": [{"text": "<simpleChoice identifier=\"id2d929434-1f63-438a-a5b3-043d05c718d5\"><p class=\"verb\">going</p></simpleChoice>", "languageTypeId": "639-2%3AENG%40ISO", "formatTypeId": "TextFormats%3APLAIN%40okapia.net", "scriptTypeId": "15924%3ALATN%40ISO"}], "id": "id2d929434-1f63-438a-a5b3-043d05c718d5", "name": ""}, {"texts": [{"text": "<simpleChoice identifier=\"idb7224104-f677-4f78-8494-76638f272b88\"><p class=\"adverb\">over</p></simpleChoice>", "languageTypeId": "639-2%3AENG%40ISO", "formatTypeId": "TextFormats%3APLAIN%40okapia.net", "scriptTypeId": "15924%3ALATN%40ISO"}], "id": "idb7224104-f677-4f78-8494-76638f272b88", "name": ""}, {"texts": [{"text": "<simpleChoice identifier=\"id2e43b2f0-2dea-4074-977c-a47b3f86d48b\"><p class=\"other\">the</p></simpleChoice>", "languageTypeId": "639-2%3AENG%40ISO", "formatTypeId": "TextFormats%3APLAIN%40okapia.net", "scriptTypeId": "15924%3ALATN%40ISO"}], "id": "id2e43b2f0-2dea-4074-977c-a47b3f86d48b", "name": ""}, {"texts": [{"text": "<simpleChoice identifier=\"id3fd2d3a4-a9ae-4ffa-a397-03ce06baf314\"><p class=\"noun\">bridge.</p></simpleChoice>", "languageTypeId": "639-2%3AENG%40ISO", "formatTypeId": "TextFormats%3APLAIN%40okapia.net", "scriptTypeId": "15924%3ALATN%40ISO"}], "id": "id3fd2d3a4-a9ae-4ffa-a397-03ce06baf314", "name": ""}], "texts": [{"text": "<itemBody><p><img alt=\"\" src=\"AssetContent:medium4425453128778916719ee_U01L05A02Px05_en_img009_1x_png\"/></p></itemBody>", "languageTypeId": "639-2%3AENG%40ISO", "formatTypeId": "TextFormats%3APLAIN%40okapia.net", "scriptTypeId": "15924%3ALATN%40ISO"}], "displayNames": [{"text": "ee_u1l05a02q04", "languageTypeId": "639-2%3AENG%40ISO", "formatTypeId": "TextFormats%3APLAIN%40okapia.net", "scriptTypeId": "15924%3ALATN%40ISO"}], "descriptions": [{"text": "ee_u1l05a02q04", "languageTypeId": "639-2%3AENG%40ISO", "formatTypeId": "TextFormats%3APLAIN%40okapia.net", "scriptTypeId": "15924%3ALATN%40ISO"}], "genusTypeId": "question-type%3Aqti-order-interaction-mw-sentence%40ODL.MIT.EDU", "assignedBankIds": ["assessment.Bank%3A57ea65d1b3fcec04647eed7e%40ODL.MIT.EDU"], "displayName": {"text": "", "languageTypeId": "639-2%3AENG%40ISO", "formatTypeId": "TextFormats%3APLAIN%40okapia.net", "scriptTypeId": "15924%3ALATN%40ISO"}, "_id": "57fd0a1bb3fcec0b1b2a4be2", "multiAnswer": false, "fileIds": {"medium4425453128778916719ee_U01L05A02Px05_en_img009_1x_png": {"assetId": "repository.Asset%3A57fd0a1bb3fcec0b1b2a4bf0%40ODL.MIT.EDU", "assetContentTypeId": "asset-content-genus-type%3Apng%40iana.org", "assetContentId": "repository.AssetContent%3A57fd0a1bb3fcec0b1b2a4bf2%40ODL.MIT.EDU"}}}, "creationTime": {"hour": 15, "month": 10, "second": 47, "microsecond": 854134, "year": 2016, "tzinfo": null, "day": 11, "minute": 49}, "answers": [{"itemId": "assessment.Item%3A57fd0a1bb3fcec0b1b2a4be2%40ODL.MIT.EDU", "displayName": {"text": "", "languageTypeId": "639-2%3AENG%40ISO", "scriptTypeId": "15924%3ALATN%40ISO", "formatTypeId": "TextFormats%3APLAIN%40okapia.net"}, "description": {"text": "", "languageTypeId": "639-2%3AENG%40ISO", "scriptTypeId": "15924%3ALATN%40ISO", "formatTypeId": "TextFormats%3APLAIN%40okapia.net"}, "recordTypeIds": ["answer-record-type%3Aqti%40ODL.MIT.EDU", "answer-record-type%3Amulti-language-answer-with-feedback%40ODL.MIT.EDU", "answer-record-type%3Afiles%40ODL.MIT.EDU", "answer-record-type%3Amulti-choice-answer%40ODL.MIT.EDU"], "choiceIds": ["idf2a31c44-9fd1-446e-b935-dd0da63f35d2", "id78c6aac9-5e58-45c3-8bc2-4f8eb2be6a83", "idf81b76d8-f298-4323-b6b9-44b22f7ce2b2", "id2db910f2-0e35-42da-9423-3f2a4968cc65", "id2d929434-1f63-438a-a5b3-043d05c718d5", "idb7224104-f677-4f78-8494-76638f272b88", "id2e43b2f0-2dea-4074-977c-a47b3f86d48b", "id3fd2d3a4-a9ae-4ffa-a397-03ce06baf314"], "genusTypeId": "answer-type%3Aright-answer%40ODL.MIT.EDU", "assignedBankIds": ["assessment.Bank%3A57ea65d1b3fcec04647eed7e%40ODL.MIT.EDU"], "_id": "57fd0a1bb3fcec0b1b2a4bf4", "feedbacks": [{"text": "<modalFeedback identifier=\"Feedback534501971\" outcomeIdentifier=\"FEEDBACKMODAL\" showHide=\"show\" title=\"ee_u1l05a02q04AF_en\"><p><span data-sheets-userformat=\"{\" data-sheets-value=\"{\">Very, very good. A school bus is going over the bridge. <br/><br/>Go ahead to the next question. </span></p></modalFeedback>", "languageTypeId": "639-2%3AENG%40ISO", "formatTypeId": "TextFormats%3APLAIN%40okapia.net", "scriptTypeId": "15924%3ALATN%40ISO"}], "fileIds": {}}, {"itemId": "assessment.Item%3A57fd0a1bb3fcec0b1b2a4be2%40ODL.MIT.EDU", "displayName": {"text": "", "languageTypeId": "639-2%3AENG%40ISO", "scriptTypeId": "15924%3ALATN%40ISO", "formatTypeId": "TextFormats%3APLAIN%40okapia.net"}, "description": {"text": "", "languageTypeId": "639-2%3AENG%40ISO", "scriptTypeId": "15924%3ALATN%40ISO", "formatTypeId": "TextFormats%3APLAIN%40okapia.net"}, "recordTypeIds": ["answer-record-type%3Aqti%40ODL.MIT.EDU", "answer-record-type%3Amulti-language-answer-with-feedback%40ODL.MIT.EDU", "answer-record-type%3Afiles%40ODL.MIT.EDU", "answer-record-type%3Amulti-choice-answer%40ODL.MIT.EDU"], "choiceIds": [null], "genusTypeId": "answer-type%3Awrong-answer%40ODL.MIT.EDU", "assignedBankIds": ["assessment.Bank%3A57ea65d1b3fcec04647eed7e%40ODL.MIT.EDU"], "_id": "57fd0a1bb3fcec0b1b2a4bf6", "feedbacks": [{"text": "<modalFeedback identifier=\"Feedback248675843\" outcomeIdentifier=\"FEEDBACKMODAL\" showHide=\"show\" title=\"ee_u1l05a02q04BF_en\"><p>Please try again</p></modalFeedback>", "languageTypeId": "639-2%3AENG%40ISO", "formatTypeId": "TextFormats%3APLAIN%40okapia.net", "scriptTypeId": "15924%3ALATN%40ISO"}], "fileIds": {}}], "texts": {}, "displayNames": [{"text": "ee_u1l05a02q04", "languageTypeId": "639-2%3AENG%40ISO", "formatTypeId": "TextFormats%3APLAIN%40okapia.net", "scriptTypeId": "15924%3ALATN%40ISO"}], "descriptions": [{"text": "QTI AssessmentItem", "languageTypeId": "639-2%3AENG%40ISO", "formatTypeId": "TextFormats%3APLAIN%40okapia.net", "scriptTypeId": "15924%3ALATN%40ISO"}], "creatorId": "", "assignedBankIds": ["assessment.Bank%3A57ea65d1b3fcec04647eed7e%40ODL.MIT.EDU"], "provenanceId": "", "genusTypeId": "item-genus-type%3Aqti-order-interaction-mw-sentence%40ODL.MIT.EDU", "_id": "57fd0a1bb3fcec0b1b2a4be2", "maxStringLength": null, "learningObjectiveIds": ["learning.Objective%3AGrade 9.A1%40CLIX.TISS.EDU"]}