{"minStringLength": null, "displayName": {"text": "", "languageTypeId": "639-2%3AENG%40ISO", "formatTypeId": "TextFormats%3APLAIN%40okapia.net", "scriptTypeId": "15924%3ALATN%40ISO"}, "description": {"text": "", "languageTypeId": "639-2%3AENG%40ISO", "formatTypeId": "TextFormats%3APLAIN%40okapia.net", "scriptTypeId": "15924%3ALATN%40ISO"}, "recordTypeIds": ["item-record-type%3Aqti%40ODL.MIT.EDU", "item-record-type%3Aprovenance%40ODL.MIT.EDU", "item-record-type%3Awrong-answer%40ODL.MIT.EDU", "osid-object%3Amulti-language%40ODL.MIT.EDU", "item-record-type%3Amulti-choice-randomized%40ODL.MIT.EDU"], "creationTime": {"hour": 6, "month": 10, "second": 11, "microsecond": 388471, "year": 2016, "tzinfo": null, "day": 5, "minute": 29}, "question": {"itemId": "assessment.Item%3A57f49db7b3fcec3154d6b15f%40ODL.MIT.EDU", "shuffle": true, "description": {"text": "", "languageTypeId": "639-2%3AENG%40ISO", "scriptTypeId": "15924%3ALATN%40ISO", "formatTypeId": "TextFormats%3APLAIN%40okapia.net"}, "recordTypeIds": ["question-record-type%3Aqti%40ODL.MIT.EDU", "osid-object%3Amulti-language%40ODL.MIT.EDU", "question-record-type%3Amulti-choice-randomized%40ODL.MIT.EDU", "question-record-type%3Amulti-language-multiple-choice%40ODL.MIT.EDU"], "text": {"text": "", "languageTypeId": "639-2%3AENG%40ISO", "formatTypeId": "TextFormats%3APLAIN%40okapia.net", "scriptTypeId": "15924%3ALATN%40ISO"}, "choices": [{"texts": [{"text": "<simpleChoice identifier=\"idb8d873b5-ee5a-4de4-bbfa-b979b42d4965\"><p><span data-sheets-userformat=\"{\" data-sheets-value=\"{\">Very easily </span></p></simpleChoice>", "languageTypeId": "639-2%3AENG%40ISO", "formatTypeId": "TextFormats%3APLAIN%40okapia.net", "scriptTypeId": "15924%3ALATN%40ISO"}], "id": "idb8d873b5-ee5a-4de4-bbfa-b979b42d4965", "name": ""}, {"texts": [{"text": "<simpleChoice identifier=\"idb69ec985-e900-495b-999b-ec618ef6eda9\"><p><span data-sheets-userformat=\"{\" data-sheets-value=\"{\">Easily </span></p></simpleChoice>", "languageTypeId": "639-2%3AENG%40ISO", "formatTypeId": "TextFormats%3APLAIN%40okapia.net", "scriptTypeId": "15924%3ALATN%40ISO"}], "id": "idb69ec985-e900-495b-999b-ec618ef6eda9", "name": ""}, {"texts": [{"text": "<simpleChoice identifier=\"idc4252946-4859-4035-aaab-d1ab9a14b5c7\"><p><span data-sheets-userformat=\"{\" data-sheets-value=\"{\">With difficulty</span></p></simpleChoice>", "languageTypeId": "639-2%3AENG%40ISO", "formatTypeId": "TextFormats%3APLAIN%40okapia.net", "scriptTypeId": "15924%3ALATN%40ISO"}], "id": "idc4252946-4859-4035-aaab-d1ab9a14b5c7", "name": ""}, {"texts": [{"text": "<simpleChoice identifier=\"ide2992843-8052-42ec-b021-bbe16bc368c4\"><p><span data-sheets-userformat=\"{\" data-sheets-value=\"{\">With great difficulty. </span></p></simpleChoice>", "languageTypeId": "639-2%3AENG%40ISO", "formatTypeId": "TextFormats%3APLAIN%40okapia.net", "scriptTypeId": "15924%3ALATN%40ISO"}], "id": "ide2992843-8052-42ec-b021-bbe16bc368c4", "name": ""}], "texts": [{"text": "<itemBody><p><span data-sheets-userformat=\"{\" data-sheets-value=\"{\">I can describe an image.</span></p></itemBody>", "languageTypeId": "639-2%3AENG%40ISO", "formatTypeId": "TextFormats%3APLAIN%40okapia.net", "scriptTypeId": "15924%3ALATN%40ISO"}], "displayNames": [{"text": "eb_u01l10a09q04", "languageTypeId": "639-2%3AENG%40ISO", "formatTypeId": "TextFormats%3APLAIN%40okapia.net", "scriptTypeId": "15924%3ALATN%40ISO"}], "descriptions": [{"text": "eb_u01l10a09q04", "languageTypeId": "639-2%3AENG%40ISO", "formatTypeId": "TextFormats%3APLAIN%40okapia.net", "scriptTypeId": "15924%3ALATN%40ISO"}], "genusTypeId": "question-type%3Aqti-choice-interaction-survey%40ODL.MIT.EDU", "assignedBankIds": ["assessment.Bank%3A57f49d8db3fcec3154d6b0e3%40ODL.MIT.EDU"], "displayName": {"text": "", "languageTypeId": "639-2%3AENG%40ISO", "scriptTypeId": "15924%3ALATN%40ISO", "formatTypeId": "TextFormats%3APLAIN%40okapia.net"}, "_id": "57f49db7b3fcec3154d6b15f", "multiAnswer": false, "fileIds": {}}, "answers": [{"itemId": "assessment.Item%3A57f49db7b3fcec3154d6b15f%40ODL.MIT.EDU", "displayName": {"text": "", "languageTypeId": "639-2%3AENG%40ISO", "scriptTypeId": "15924%3ALATN%40ISO", "formatTypeId": "TextFormats%3APLAIN%40okapia.net"}, "description": {"text": "", "languageTypeId": "639-2%3AENG%40ISO", "scriptTypeId": "15924%3ALATN%40ISO", "formatTypeId": "TextFormats%3APLAIN%40okapia.net"}, "recordTypeIds": ["answer-record-type%3Aqti%40ODL.MIT.EDU", "answer-record-type%3Amulti-language-answer-with-feedback%40ODL.MIT.EDU", "answer-record-type%3Afiles%40ODL.MIT.EDU", "answer-record-type%3Amulti-choice-answer%40ODL.MIT.EDU"], "choiceIds": ["idb8d873b5-ee5a-4de4-bbfa-b979b42d4965"], "genusTypeId": "answer-type%3Aright-answer%40ODL.MIT.EDU", "assignedBankIds": ["assessment.Bank%3A57f49d8db3fcec3154d6b0e3%40ODL.MIT.EDU"], "_id": "57f49db7b3fcec3154d6b16d", "feedbacks": [{"text": "<modalFeedback  identifier=\"Feedback\" outcomeIdentifier=\"FEEDBACKMODAL\" showHide=\"show\">\n<p></p>\n</modalFeedback>", "languageTypeId": "639-2%3AENG%40ISO", "formatTypeId": "TextFormats%3APLAIN%40okapia.net", "scriptTypeId": "15924%3ALATN%40ISO"}], "fileIds": {}}, {"itemId": "assessment.Item%3A57f49db7b3fcec3154d6b15f%40ODL.MIT.EDU", "displayName": {"text": "", "languageTypeId": "639-2%3AENG%40ISO", "scriptTypeId": "15924%3ALATN%40ISO", "formatTypeId": "TextFormats%3APLAIN%40okapia.net"}, "description": {"text": "", "languageTypeId": "639-2%3AENG%40ISO", "scriptTypeId": "15924%3ALATN%40ISO", "formatTypeId": "TextFormats%3APLAIN%40okapia.net"}, "recordTypeIds": ["answer-record-type%3Aqti%40ODL.MIT.EDU", "answer-record-type%3Amulti-language-answer-with-feedback%40ODL.MIT.EDU", "answer-record-type%3Afiles%40ODL.MIT.EDU", "answer-record-type%3Amulti-choice-answer%40ODL.MIT.EDU"], "choiceIds": ["idb69ec985-e900-495b-999b-ec618ef6eda9"], "genusTypeId": "answer-type%3Aright-answer%40ODL.MIT.EDU", "assignedBankIds": ["assessment.Bank%3A57f49d8db3fcec3154d6b0e3%40ODL.MIT.EDU"], "_id": "57f49db7b3fcec3154d6b16f", "feedbacks": [{"text": "<modalFeedback  identifier=\"Feedback\" outcomeIdentifier=\"FEEDBACKMODAL\" showHide=\"show\">\n<p></p>\n</modalFeedback>", "languageTypeId": "639-2%3AENG%40ISO", "formatTypeId": "TextFormats%3APLAIN%40okapia.net", "scriptTypeId": "15924%3ALATN%40ISO"}], "fileIds": {}}, {"itemId": "assessment.Item%3A57f49db7b3fcec3154d6b15f%40ODL.MIT.EDU", "displayName": {"text": "", "languageTypeId": "639-2%3AENG%40ISO", "scriptTypeId": "15924%3ALATN%40ISO", "formatTypeId": "TextFormats%3APLAIN%40okapia.net"}, "description": {"text": "", "languageTypeId": "639-2%3AENG%40ISO", "scriptTypeId": "15924%3ALATN%40ISO", "formatTypeId": "TextFormats%3APLAIN%40okapia.net"}, "recordTypeIds": ["answer-record-type%3Aqti%40ODL.MIT.EDU", "answer-record-type%3Amulti-language-answer-with-feedback%40ODL.MIT.EDU", "answer-record-type%3Afiles%40ODL.MIT.EDU", "answer-record-type%3Amulti-choice-answer%40ODL.MIT.EDU"], "choiceIds": ["ide2992843-8052-42ec-b021-bbe16bc368c4"], "genusTypeId": "answer-type%3Aright-answer%40ODL.MIT.EDU", "assignedBankIds": ["assessment.Bank%3A57f49d8db3fcec3154d6b0e3%40ODL.MIT.EDU"], "_id": "57f49db7b3fcec3154d6b171", "feedbacks": [{"text": "<modalFeedback  identifier=\"Feedback\" outcomeIdentifier=\"FEEDBACKMODAL\" showHide=\"show\">\n<p></p>\n</modalFeedback>", "languageTypeId": "639-2%3AENG%40ISO", "formatTypeId": "TextFormats%3APLAIN%40okapia.net", "scriptTypeId": "15924%3ALATN%40ISO"}], "fileIds": {}}, {"itemId": "assessment.Item%3A57f49db7b3fcec3154d6b15f%40ODL.MIT.EDU", "displayName": {"text": "", "languageTypeId": "639-2%3AENG%40ISO", "scriptTypeId": "15924%3ALATN%40ISO", "formatTypeId": "TextFormats%3APLAIN%40okapia.net"}, "description": {"text": "", "languageTypeId": "639-2%3AENG%40ISO", "scriptTypeId": "15924%3ALATN%40ISO", "formatTypeId": "TextFormats%3APLAIN%40okapia.net"}, "recordTypeIds": ["answer-record-type%3Aqti%40ODL.MIT.EDU", "answer-record-type%3Amulti-language-answer-with-feedback%40ODL.MIT.EDU", "answer-record-type%3Afiles%40ODL.MIT.EDU", "answer-record-type%3Amulti-choice-answer%40ODL.MIT.EDU"], "choiceIds": ["idc4252946-4859-4035-aaab-d1ab9a14b5c7"], "genusTypeId": "answer-type%3Aright-answer%40ODL.MIT.EDU", "assignedBankIds": ["assessment.Bank%3A57f49d8db3fcec3154d6b0e3%40ODL.MIT.EDU"], "_id": "57f49db7b3fcec3154d6b173", "feedbacks": [{"text": "<modalFeedback  identifier=\"Feedback\" outcomeIdentifier=\"FEEDBACKMODAL\" showHide=\"show\">\n<p></p>\n</modalFeedback>", "languageTypeId": "639-2%3AENG%40ISO", "formatTypeId": "TextFormats%3APLAIN%40okapia.net", "scriptTypeId": "15924%3ALATN%40ISO"}], "fileIds": {}}], "texts": {}, "displayNames": [{"text": "eb_u01l10a09q04", "languageTypeId": "639-2%3AENG%40ISO", "formatTypeId": "TextFormats%3APLAIN%40okapia.net", "scriptTypeId": "15924%3ALATN%40ISO"}], "descriptions": [{"text": "QTI AssessmentItem", "languageTypeId": "639-2%3AENG%40ISO", "formatTypeId": "TextFormats%3APLAIN%40okapia.net", "scriptTypeId": "15924%3ALATN%40ISO"}], "creatorId": "", "assignedBankIds": ["assessment.Bank%3A57f49d8db3fcec3154d6b0e3%40ODL.MIT.EDU"], "provenanceId": "", "genusTypeId": "item-genus-type%3Aqti-choice-interaction-survey%40ODL.MIT.EDU", "_id": "57f49db7b3fcec3154d6b15f", "maxStringLength": null, "learningObjectiveIds": []}